ledworks/__init__.py
ledworks/animation.py
ledworks/filterbank.py
ledworks/led.py
ledworks/player.py
ledworks/rate.py
ledworks/strip.py
ledworks/timers.py
ledworks/utils.py
ledworks-0.0.1.dist-info/METADATA
ledworks-0.0.1.dist-info/WHEEL
ledworks-0.0.1.dist-info/top_level.txt
ledworks-0.0.1.dist-info/RECORD
