Metadata-Version: 2.1
Name: ledworks
Version: 0.0.1
Summary: Library for creating LED strip animations.
Home-page: https://github.com/Run1e/ledworks
Author: RUNIE
Author-email: runar-borge@hotmail.com
License: UNKNOWN
Platform: UNKNOWN
Classifier: Programming Language :: Python :: 3
Classifier: License :: OSI Approved :: MIT License
Classifier: Operating System :: OS Independent
Requires-Python: >=3.6
